Metadata-Version: 1.0
Name: xychan
Version: 0.3
Summary: A 'chan-style' web message board similar to Wakaba
Home-page: http://mike.verdone.ca/xychan
Author: Mike Verdone
Author-email: mike.verdone@gmail.com
License: GNU General Public License v3 (GPL)
Keywords: 4chan,chan,message board,Wakaba
Platform: UNKNOWN
Classifier: Development Status :: 4 - Beta
Classifier: Environment :: Web Environment
Classifier: License :: OSI Approved :: GNU General Public License (GPL)
Classifier: Natural Language :: English
Classifier: Operating System :: POSIX
Classifier: Programming Language :: Python
Classifier: Topic :: Communications :: BBS
Classifier: Topic :: Internet :: WWW/HTTP :: WSGI :: Application
